biobase/analysis/__init__.py
biobase/analysis/motif.py
biobase/analysis/nucleic_analysis.py
biobase/constants/__init__.py
biobase/constants/amino_acid.py
biobase/constants/nucleic_acid.py
biobase/constants/rna_seq.py
biobase/matrix/__init__.py
biobase/matrix/sub_matrix.py
biobase/matrix/matrices/BLOSUM30.json
biobase/matrix/matrices/BLOSUM35.json
biobase/matrix/matrices/BLOSUM40.json
biobase/matrix/matrices/BLOSUM45.json
biobase/matrix/matrices/BLOSUM50.json
biobase/matrix/matrices/BLOSUM55.json
biobase/matrix/matrices/BLOSUM60.json
biobase/matrix/matrices/BLOSUM62.json
biobase/matrix/matrices/BLOSUM65.json
biobase/matrix/matrices/BLOSUM70.json
biobase/matrix/matrices/BLOSUM75.json
biobase/matrix/matrices/BLOSUM80.json
biobase/matrix/matrices/BLOSUM85.json
biobase/matrix/matrices/BLOSUM90.json
biobase/matrix/matrices/IDENTITY-10000.json
biobase/matrix/matrices/IDENTITY0.json
biobase/matrix/matrices/MATCH.json
biobase/matrix/matrices/PAM10.json
biobase/matrix/matrices/PAM100.json
biobase/matrix/matrices/PAM110.json
biobase/matrix/matrices/PAM120.json
biobase/matrix/matrices/PAM160.json
biobase/matrix/matrices/PAM170.json
biobase/matrix/matrices/PAM200.json
biobase/matrix/matrices/PAM250.json
biobase/matrix/matrices/PAM30.json
biobase/matrix/matrices/PAM300.json
biobase/matrix/matrices/PAM400.json
biobase/matrix/matrices/PAM450.json
biobase/matrix/matrices/PAM50.json
biobase/matrix/matrices/PAM500.json
biobase/matrix/matrices/PAM60.json
biobase/matrix/matrices/PAM70.json
biobase/matrix/matrices/PAM80.json
biobase/matrix/matrices/PAM90.json
biobase/matrix/matrices/__init__.py
biobase/parser/__init__.py
biobase/parser/fasta.py
biobase/parser/fastq.py
biobase-0.9.0.dist-info/METADATA
biobase-0.9.0.dist-info/WHEEL
biobase-0.9.0.dist-info/licenses/LICENSE
biobase-0.9.0.dist-info/RECORD
