Metadata-Version: 2.4
Name: biobase
Version: 0.9.0
Summary: A comprehensive package of biological constants, serving as a foundational resource for biology and bioinformatics, complemented by functions to streamline related tasks.
Project-URL: Homepage, https://github.com/lignum-vitae/biobase
Project-URL: Issues, https://github.com/lignum-vitae/biobase/issues
Author-email: Andrew Hennis <andrew.mr.hennis@gmail.com>
License: MIT
License-File: LICENSE
Classifier: License :: OSI Approved :: MIT License
Classifier: Operating System :: OS Independent
Classifier: Programming Language :: Python :: 3
Requires-Python: >=3.10
Requires-Dist: numpy>=2.2.6
Provides-Extra: dev
Requires-Dist: pytest; extra == 'dev'
